ATWG/ATWG.py
ATWG/__init__.py
ATWG/driver/__init__.py
ATWG/driver/espec/__init__.py
ATWG/driver/espec/sh641.py
ATWG/driver/espec/sh641Const.py
ATWG/driver/espec/sh641InterfaceDefault.yml
ATWG/driver/sim/__init__.py
ATWG/driver/sim/simChamber.py
ATWG/waves/__init__.py
ATWG/waves/waves.py
ATWG-0.1.5.data/scripts/atwg-cli
ATWG-0.1.5.dist-info/LICENSE
ATWG-0.1.5.dist-info/METADATA
ATWG-0.1.5.dist-info/WHEEL
ATWG-0.1.5.dist-info/top_level.txt
ATWG-0.1.5.dist-info/RECORD
