Metadata-Version: 2.1
Name: ATWG
Version: 0.1.5
Summary: Arbitrary Temperature Waveform Generator for Climate Chambers
Home-page: https://github.com/akaeba/ATWG
Author: Andreas Kaeberlein
Author-email: andreas.kaeberlein@web.de
License: GPLv3
Download-URL: https://pypi.org/project/ATWG/
Platform: Any
Classifier: Programming Language :: Python :: 3
Classifier: License :: OSI Approved :: GNU General Public License v3 or later (GPLv3+)
Classifier: Operating System :: OS Independent
Requires-Python: >=3.7
License-File: LICENSE
Requires-Dist: pyserial
Requires-Dist: pyyaml
